shellpomodoro/__init__.py
shellpomodoro/cli.py
shellpomodoro/display.py
shellpomodoro/ipc.py
shellpomodoro/keypress.py
shellpomodoro/models.py
shellpomodoro/runtime.py
shellpomodoro/server.py
shellpomodoro/timer.py
shellpomodoro-0.1.5.dist-info/licenses/LICENSE
shellpomodoro-0.1.5.dist-info/METADATA
shellpomodoro-0.1.5.dist-info/WHEEL
shellpomodoro-0.1.5.dist-info/entry_points.txt
shellpomodoro-0.1.5.dist-info/top_level.txt
shellpomodoro-0.1.5.dist-info/RECORD
