Metadata-Version: 2.4
Name: shellpomodoro
Version: 0.1.5
Summary: A cross-platform terminal Pomodoro timer (stdlib-only) with keypress pauses and an ASCII reward banner.
Author: Avi
License: MIT
Project-URL: Homepage, https://github.com/inspiringsource/shellpomodoro
Project-URL: Repository, https://github.com/inspiringsource/shellpomodoro
Project-URL: Issues, https://github.com/inspiringsource/shellpomodoro/issues
Keywords: pomodoro,cli,timer,productivity,terminal
Classifier: Programming Language :: Python :: 3
Classifier: Programming Language :: Python :: 3 :: Only
Classifier: Programming Language :: Python :: 3.9
Classifier: Programming Language :: Python :: 3.10
Classifier: Programming Language :: Python :: 3.11
Classifier: Programming Language :: Python :: 3.12
Classifier: License :: OSI Approved :: MIT License
Classifier: Operating System :: OS Independent
Classifier: Environment :: Console
Classifier: Intended Audience :: End Users/Desktop
Classifier: Topic :: Utilities
Requires-Python: >=3.9
License-File: LICENSE
Dynamic: license-file
